betteryeah/__init__.py
betteryeah/api_client.py
betteryeah/api_response.py
betteryeah/core.py
betteryeah/utils.py
betteryeah/version.py
betteryeah/database/__init__.py
betteryeah/database/response.py
betteryeah/knowledge/__init__.py
betteryeah/knowledge/request.py
betteryeah/knowledge/response.py
betteryeah/llm/__init__.py
betteryeah/llm/request.py
betteryeah/llm/response.py
betteryeah/plugin/__init__.py
betteryeah/plugin/bilibili/__init__.py
betteryeah/plugin/bilibili/request.py
betteryeah/plugin/bilibili/response.py
betteryeah/plugin/douyin/__init__.py
betteryeah/plugin/douyin/request.py
betteryeah/plugin/douyin/response.py
betteryeah/plugin/generic/__init__.py
betteryeah/plugin/generic/request.py
betteryeah/plugin/generic/response.py
betteryeah/plugin/image/__init__.py
betteryeah/plugin/image/request.py
betteryeah/plugin/image/response.py
betteryeah/plugin/knowledgeqa/__init__.py
betteryeah/plugin/knowledgeqa/request.py
betteryeah/plugin/knowledgeqa/response.py
betteryeah/plugin/parsing/__init__.py
betteryeah/plugin/parsing/request.py
betteryeah/plugin/parsing/response.py
betteryeah/plugin/search/__init__.py
betteryeah/plugin/search/request.py
betteryeah/plugin/search/response.py
betteryeah/plugin/toutiao/__init__.py
betteryeah/plugin/toutiao/request.py
betteryeah/plugin/toutiao/response.py
betteryeah/plugin/weibo/__init__.py
betteryeah/plugin/weibo/response.py
betteryeah/plugin/xiaohongshu/__init__.py
betteryeah/plugin/xiaohongshu/response.py
betteryeah/plugin/zhihu/__init__.py
betteryeah/plugin/zhihu/response.py
betteryeah/sub_flow/__init__.py
betteryeah/sub_flow/response.py
betteryeah-0.2.23.dist-info/licenses/LICENSE
test/__init__.py
test/database/__init__.py
test/knowledge/__init__.py
test/llm/__init__.py
test/sub_flow/__init__.py
betteryeah-0.2.23.dist-info/METADATA
betteryeah-0.2.23.dist-info/WHEEL
betteryeah-0.2.23.dist-info/top_level.txt
betteryeah-0.2.23.dist-info/RECORD
